[
    {
        "cells": [
            {
                "pdf_text_tight_bbox": [
                    256.59100341796875,
                    206.41184997558594,
                    270.59100341796875,
                    213.41184997558594
                ],
                "text_content": "2011",
                "row_nums": [
                    0
                ],
                "column_nums": [
                    1
                ],
                "is_column_header": true,
                "is_projected_row_header": false,
                "pdf_bbox": [
                    256.59100341796875,
                    206.41184997558594,
                    270.60589599609375,
                    213.41184997558594
                ],
                "pdf_text_content": "2011"
            },
            {
                "pdf_text_tight_bbox": [
                    286.0533142089844,
                    206.41184997558594,
                    300.0533142089844,
                    213.41184997558594
                ],
                "text_content": "2012",
                "row_nums": [
                    0
                ],
                "column_nums": [
                    2
                ],
                "is_column_header": true,
                "is_projected_row_header": false,
                "pdf_bbox": [
                    286.0533142089844,
                    206.41184997558594,
                    300.0682067871094,
                    213.41184997558594
                ],
                "pdf_text_content": "2012"
            },
            {
                "pdf_text_tight_bbox": [
                    315.515625,
                    206.41184997558594,
                    329.515625,
                    213.41184997558594
                ],
                "text_content": "2013",
                "row_nums": [
                    0
                ],
                "column_nums": [
                    3
                ],
                "is_column_header": true,
                "is_projected_row_header": false,
                "pdf_bbox": [
                    315.515625,
                    206.41184997558594,
                    329.530517578125,
                    213.41184997558594
                ],
                "pdf_text_content": "2013"
            },
            {
                "pdf_text_tight_bbox": [
                    344.9779357910156,
                    206.41184997558594,
                    358.9779357910156,
                    213.41184997558594
                ],
                "text_content": "2014",
                "row_nums": [
                    0
                ],
                "column_nums": [
                    4
                ],
                "is_column_header": true,
                "is_projected_row_header": false,
                "pdf_bbox": [
                    344.9779357910156,
                    206.41184997558594,
                    358.9928283691406,
                    213.41184997558594
                ],
                "pdf_text_content": "2014"
            },
            {
                "pdf_text_tight_bbox": [
                    374.44024658203125,
                    206.41184997558594,
                    388.44024658203125,
                    213.41184997558594
                ],
                "text_content": "2015",
                "row_nums": [
                    0
                ],
                "column_nums": [
                    5
                ],
                "is_column_header": true,
                "is_projected_row_header": false,
                "pdf_bbox": [
                    374.44024658203125,
                    206.41184997558594,
                    388.45513916015625,
                    213.41184997558594
                ],
                "pdf_text_content": "2015"
            },
            {
                "pdf_text_tight_bbox": [
                    403.9025573730469,
                    206.41184997558594,
                    417.9025573730469,
                    213.41184997558594
                ],
                "text_content": "2016",
                "row_nums": [
                    0
                ],
                "column_nums": [
                    6
                ],
                "is_column_header": true,
                "is_projected_row_header": false,
                "pdf_bbox": [
                    403.9025573730469,
                    206.41184997558594,
                    417.9174499511719,
                    213.41184997558594
                ],
                "pdf_text_content": "2016"
            },
            {
                "pdf_text_tight_bbox": [
                    433.3648681640625,
                    206.41184997558594,
                    447.3648681640625,
                    213.41184997558594
                ],
                "text_content": "2017",
                "row_nums": [
                    0
                ],
                "column_nums": [
                    7
                ],
                "is_column_header": true,
                "is_projected_row_header": false,
                "pdf_bbox": [
                    433.3648681640625,
                    206.41184997558594,
                    447.3797607421875,
                    213.41184997558594
                ],
                "pdf_text_content": "2017"
            },
            {
                "pdf_text_tight_bbox": [
                    462.8257751464844,
                    206.41184997558594,
                    476.8257751464844,
                    213.41184997558594
                ],
                "text_content": "2018",
                "row_nums": [
                    0
                ],
                "column_nums": [
                    8
                ],
                "is_column_header": true,
                "is_projected_row_header": false,
                "pdf_bbox": [
                    462.8257751464844,
                    206.41184997558594,
                    476.8406677246094,
                    213.41184997558594
                ],
                "pdf_text_content": "2018"
            },
            {
                "pdf_text_tight_bbox": [
                    492.2880859375,
                    206.41184997558594,
                    506.2880859375,
                    213.41184997558594
                ],
                "text_content": "2019",
                "row_nums": [
                    0
                ],
                "column_nums": [
                    9
                ],
                "is_column_header": true,
                "is_projected_row_header": false,
                "pdf_bbox": [
                    492.2880859375,
                    206.41184997558594,
                    506.302978515625,
                    213.41184997558594
                ],
                "pdf_text_content": "2019"
            },
            {
                "pdf_text_tight_bbox": [
                    521.7503662109375,
                    206.41184997558594,
                    535.7503662109375,
                    213.41184997558594
                ],
                "text_content": "2020",
                "row_nums": [
                    0
                ],
                "column_nums": [
                    10
                ],
                "is_column_header": true,
                "is_projected_row_header": false,
                "pdf_bbox": [
                    521.7503662109375,
                    206.41184997558594,
                    535.7652587890625,
                    213.41184997558594
                ],
                "pdf_text_content": "2020"
            },
            {
                "pdf_text_tight_bbox": [
                    150.23599243164062,
                    219.73983764648438,
                    200.3979949951172,
                    226.73983764648438
                ],
                "text_content": "Real GDP growth",
                "row_nums": [
                    1
                ],
                "column_nums": [
                    0
                ],
                "is_column_header": false,
                "is_projected_row_header": false,
                "pdf_bbox": [
                    150.23599243164062,
                    219.73983764648438,
                    238.49899291992188,
                    226.73983764648438
                ],
                "pdf_text_content": "Real GDP growth"
            },
            {
                "pdf_text_tight_bbox": [
                    259.51019287109375,
                    219.73983764648438,
                    270.5911865234375,
                    226.73983764648438
                ],
                "text_content": "-1.6",
                "row_nums": [
                    1
                ],
                "column_nums": [
                    1
                ],
                "is_column_header": false,
                "is_projected_row_header": false,
                "pdf_bbox": [
                    256.59100341796875,
                    219.73983764648438,
                    270.60589599609375,
                    226.73983764648438
                ],
                "pdf_text_content": "-1.6"
            },
            {
                "pdf_text_tight_bbox": [
                    288.9718017578125,
                    219.73983764648438,
                    300.05279541015625,
                    226.73983764648438
                ],
                "text_content": "-3.3",
                "row_nums": [
                    1
                ],
                "column_nums": [
                    2
                ],
                "is_column_header": false,
                "is_projected_row_header": false,
                "pdf_bbox": [
                    286.0533142089844,
                    219.73983764648438,
                    300.0682067871094,
                    226.73983764648438
                ],
                "pdf_text_content": "-3.3"
            },
            {
                "pdf_text_tight_bbox": [
                    320.7651062011719,
                    219.73983764648438,
                    329.5151062011719,
                    226.73983764648438
                ],
                "text_content": "0.3",
                "row_nums": [
                    1
                ],
                "column_nums": [
                    3
                ],
                "is_column_header": false,
                "is_projected_row_header": false,
                "pdf_bbox": [
                    315.515625,
                    219.73983764648438,
                    329.530517578125,
                    226.73983764648438
                ],
                "pdf_text_content": "0.3"
            },
            {
                "pdf_text_tight_bbox": [
                    350.2274169921875,
                    219.73983764648438,
                    358.9774169921875,
                    226.73983764648438
                ],
                "text_content": "2.1",
                "row_nums": [
                    1
                ],
                "column_nums": [
                    4
                ],
                "is_column_header": false,
                "is_projected_row_header": false,
                "pdf_bbox": [
                    344.9779357910156,
                    219.73983764648438,
                    358.9928283691406,
                    226.73983764648438
                ],
                "pdf_text_content": "2.1"
            },
            {
                "pdf_text_tight_bbox": [
                    379.6897277832031,
                    219.73983764648438,
                    388.4397277832031,
                    226.73983764648438
                ],
                "text_content": "2.0",
                "row_nums": [
                    1
                ],
                "column_nums": [
                    5
                ],
                "is_column_header": false,
                "is_projected_row_header": false,
                "pdf_bbox": [
                    374.44024658203125,
                    219.73983764648438,
                    388.45513916015625,
                    226.73983764648438
                ],
                "pdf_text_content": "2.0"
            },
            {
                "pdf_text_tight_bbox": [
                    409.15203857421875,
                    219.73983764648438,
                    417.90203857421875,
                    226.73983764648438
                ],
                "text_content": "1.8",
                "row_nums": [
                    1
                ],
                "column_nums": [
                    6
                ],
                "is_column_header": false,
                "is_projected_row_header": false,
                "pdf_bbox": [
                    403.9025573730469,
                    219.73983764648438,
                    417.9174499511719,
                    226.73983764648438
                ],
                "pdf_text_content": "1.8"
            },
            {
                "pdf_text_tight_bbox": [
                    438.6143493652344,
                    219.73983764648438,
                    447.3643493652344,
                    226.73983764648438
                ],
                "text_content": "1.6",
                "row_nums": [
                    1
                ],
                "column_nums": [
                    7
                ],
                "is_column_header": false,
                "is_projected_row_header": false,
                "pdf_bbox": [
                    433.3648681640625,
                    219.73983764648438,
                    447.3797607421875,
                    226.73983764648438
                ],
                "pdf_text_content": "1.6"
            },
            {
                "pdf_text_tight_bbox": [
                    468.07525634765625,
                    219.73983764648438,
                    476.82525634765625,
                    226.73983764648438
                ],
                "text_content": "1.6",
                "row_nums": [
                    1
                ],
                "column_nums": [
                    8
                ],
                "is_column_header": false,
                "is_projected_row_header": false,
                "pdf_bbox": [
                    462.8257751464844,
                    219.73983764648438,
                    476.8406677246094,
                    226.73983764648438
                ],
                "pdf_text_content": "1.6"
            },
            {
                "pdf_text_tight_bbox": [
                    497.5375671386719,
                    219.73983764648438,
                    506.2875671386719,
                    226.73983764648438
                ],
                "text_content": "1.6",
                "row_nums": [
                    1
                ],
                "column_nums": [
                    9
                ],
                "is_column_header": false,
                "is_projected_row_header": false,
                "pdf_bbox": [
                    492.2880859375,
                    219.73983764648438,
                    506.302978515625,
                    226.73983764648438
                ],
                "pdf_text_content": "1.6"
            },
            {
                "pdf_text_tight_bbox": [
                    526.9998779296875,
                    219.73983764648438,
                    535.7498779296875,
                    226.73983764648438
                ],
                "text_content": "1.6",
                "row_nums": [
                    1
                ],
                "column_nums": [
                    10
                ],
                "is_column_header": false,
                "is_projected_row_header": false,
                "pdf_bbox": [
                    521.7503662109375,
                    219.73983764648438,
                    535.7652587890625,
                    226.73983764648438
                ],
                "pdf_text_content": "1.6"
            },
            {
                "pdf_text_tight_bbox": [
                    150.23599243164062,
                    228.84475708007812,
                    208.9554901123047,
                    235.84475708007812
                ],
                "text_content": "GDP deflator growth",
                "row_nums": [
                    2
                ],
                "column_nums": [
                    0
                ],
                "is_column_header": false,
                "is_projected_row_header": false,
                "pdf_bbox": [
                    150.23599243164062,
                    228.84475708007812,
                    238.49899291992188,
                    235.84475708007812
                ],
                "pdf_text_content": "GDP deﬂ ator growth"
            },
            {
                "pdf_text_tight_bbox": [
                    261.8432922363281,
                    228.84475708007812,
                    270.5932922363281,
                    235.84475708007812
                ],
                "text_content": "0.7",
                "row_nums": [
                    2
                ],
                "column_nums": [
                    1
                ],
                "is_column_header": false,
                "is_projected_row_header": false,
                "pdf_bbox": [
                    256.59100341796875,
                    228.84475708007812,
                    270.60589599609375,
                    235.84475708007812
                ],
                "pdf_text_content": "0.7"
            },
            {
                "pdf_text_tight_bbox": [
                    291.30560302734375,
                    228.84475708007812,
                    300.05560302734375,
                    235.84475708007812
                ],
                "text_content": "1.1",
                "row_nums": [
                    2
                ],
                "column_nums": [
                    2
                ],
                "is_column_header": false,
                "is_projected_row_header": false,
                "pdf_bbox": [
                    286.0533142089844,
                    228.84475708007812,
                    300.0682067871094,
                    235.84475708007812
                ],
                "pdf_text_content": "1.1"
            },
            {
                "pdf_text_tight_bbox": [
                    320.7679138183594,
                    228.84475708007812,
                    329.5179138183594,
                    235.84475708007812
                ],
                "text_content": "1.2",
                "row_nums": [
                    2
                ],
                "column_nums": [
                    3
                ],
                "is_column_header": false,
                "is_projected_row_header": false,
                "pdf_bbox": [
                    315.515625,
                    228.84475708007812,
                    329.530517578125,
                    235.84475708007812
                ],
                "pdf_text_content": "1.2"
            },
            {
                "pdf_text_tight_bbox": [
                    350.230224609375,
                    228.84475708007812,
                    358.980224609375,
                    235.84475708007812
                ],
                "text_content": "1.4",
                "row_nums": [
                    2
                ],
                "column_nums": [
                    4
                ],
                "is_column_header": false,
                "is_projected_row_header": false,
                "pdf_bbox": [
                    344.9779357910156,
                    228.84475708007812,
                    358.9928283691406,
                    235.84475708007812
                ],
                "pdf_text_content": "1.4"
            },
            {
                "pdf_text_tight_bbox": [
                    379.6925354003906,
                    228.84475708007812,
                    388.4425354003906,
                    235.84475708007812
                ],
                "text_content": "1.5",
                "row_nums": [
                    2
                ],
                "column_nums": [
                    5
                ],
                "is_column_header": false,
                "is_projected_row_header": false,
                "pdf_bbox": [
                    374.44024658203125,
                    228.84475708007812,
                    388.45513916015625,
                    235.84475708007812
                ],
                "pdf_text_content": "1.5"
            },
            {
                "pdf_text_tight_bbox": [
                    409.15484619140625,
                    228.84475708007812,
                    417.90484619140625,
                    235.84475708007812
                ],
                "text_content": "1.5",
                "row_nums": [
                    2
                ],
                "column_nums": [
                    6
                ],
                "is_column_header": false,
                "is_projected_row_header": false,
                "pdf_bbox": [
                    403.9025573730469,
                    228.84475708007812,
                    417.9174499511719,
                    235.84475708007812
                ],
                "pdf_text_content": "1.5"
            },
            {
                "pdf_text_tight_bbox": [
                    438.6171569824219,
                    228.84475708007812,
                    447.3671569824219,
                    235.84475708007812
                ],
                "text_content": "1.5",
                "row_nums": [
                    2
                ],
                "column_nums": [
                    7
                ],
                "is_column_header": false,
                "is_projected_row_header": false,
                "pdf_bbox": [
                    433.3648681640625,
                    228.84475708007812,
                    447.3797607421875,
                    235.84475708007812
                ],
                "pdf_text_content": "1.5"
            },
            {
                "pdf_text_tight_bbox": [
                    468.07806396484375,
                    228.84475708007812,
                    476.82806396484375,
                    235.84475708007812
                ],
                "text_content": "1.5",
                "row_nums": [
                    2
                ],
                "column_nums": [
                    8
                ],
                "is_column_header": false,
                "is_projected_row_header": false,
                "pdf_bbox": [
                    462.8257751464844,
                    228.84475708007812,
                    476.8406677246094,
                    235.84475708007812
                ],
                "pdf_text_content": "1.5"
            },
            {
                "pdf_text_tight_bbox": [
                    497.5403747558594,
                    228.84475708007812,
                    506.2903747558594,
                    235.84475708007812
                ],
                "text_content": "1.7",
                "row_nums": [
                    2
                ],
                "column_nums": [
                    9
                ],
                "is_column_header": false,
                "is_projected_row_header": false,
                "pdf_bbox": [
                    492.2880859375,
                    228.84475708007812,
                    506.302978515625,
                    235.84475708007812
                ],
                "pdf_text_content": "1.7"
            },
            {
                "pdf_text_tight_bbox": [
                    527.002685546875,
                    228.84475708007812,
                    535.752685546875,
                    235.84475708007812
                ],
                "text_content": "1.7",
                "row_nums": [
                    2
                ],
                "column_nums": [
                    10
                ],
                "is_column_header": false,
                "is_projected_row_header": false,
                "pdf_bbox": [
                    521.7503662109375,
                    228.84475708007812,
                    535.7652587890625,
                    235.84475708007812
                ],
                "pdf_text_content": "1.7"
            },
            {
                "pdf_text_tight_bbox": [
                    150.2360076904297,
                    237.95034790039062,
                    234.6069793701172,
                    244.95034790039062
                ],
                "text_content": "Primary balance-to-GDP ratio",
                "row_nums": [
                    3
                ],
                "column_nums": [
                    0
                ],
                "is_column_header": false,
                "is_projected_row_header": false,
                "pdf_bbox": [
                    150.23599243164062,
                    237.95034790039062,
                    238.49899291992188,
                    244.95034790039062
                ],
                "pdf_text_content": "Primary balance-to-GDP ratio"
            },
            {
                "pdf_text_tight_bbox": [
                    261.8495788574219,
                    237.95034790039062,
                    270.5995788574219,
                    244.95034790039062
                ],
                "text_content": "0.1",
                "row_nums": [
                    3
                ],
                "column_nums": [
                    1
                ],
                "is_column_header": false,
                "is_projected_row_header": false,
                "pdf_bbox": [
                    256.59100341796875,
                    237.95034790039062,
                    270.60589599609375,
                    244.95034790039062
                ],
                "pdf_text_content": "0.1"
            },
            {
                "pdf_text_tight_bbox": [
                    291.3118896484375,
                    237.95034790039062,
                    300.0618896484375,
                    244.95034790039062
                ],
                "text_content": "0.5",
                "row_nums": [
                    3
                ],
                "column_nums": [
                    2
                ],
                "is_column_header": false,
                "is_projected_row_header": false,
                "pdf_bbox": [
                    286.0533142089844,
                    237.95034790039062,
                    300.0682067871094,
                    244.95034790039062
                ],
                "pdf_text_content": "0.5"
            },
            {
                "pdf_text_tight_bbox": [
                    320.7742004394531,
                    237.95034790039062,
                    329.5242004394531,
                    244.95034790039062
                ],
                "text_content": "2.2",
                "row_nums": [
                    3
                ],
                "column_nums": [
                    3
                ],
                "is_column_header": false,
                "is_projected_row_header": false,
                "pdf_bbox": [
                    315.515625,
                    237.95034790039062,
                    329.530517578125,
                    244.95034790039062
                ],
                "pdf_text_content": "2.2"
            },
            {
                "pdf_text_tight_bbox": [
                    350.23651123046875,
                    237.95034790039062,
                    358.98651123046875,
                    244.95034790039062
                ],
                "text_content": "3.3",
                "row_nums": [
                    3
                ],
                "column_nums": [
                    4
                ],
                "is_column_header": false,
                "is_projected_row_header": false,
                "pdf_bbox": [
                    344.9779357910156,
                    237.95034790039062,
                    358.9928283691406,
                    244.95034790039062
                ],
                "pdf_text_content": "3.3"
            },
            {
                "pdf_text_tight_bbox": [
                    379.6988220214844,
                    237.95034790039062,
                    388.4488220214844,
                    244.95034790039062
                ],
                "text_content": "4.5",
                "row_nums": [
                    3
                ],
                "column_nums": [
                    5
                ],
                "is_column_header": false,
                "is_projected_row_header": false,
                "pdf_bbox": [
                    374.44024658203125,
                    237.95034790039062,
                    388.45513916015625,
                    244.95034790039062
                ],
                "pdf_text_content": "4.5"
            },
            {
                "pdf_text_tight_bbox": [
                    409.1611328125,
                    237.95034790039062,
                    417.9111328125,
                    244.95034790039062
                ],
                "text_content": "4.4",
                "row_nums": [
                    3
                ],
                "column_nums": [
                    6
                ],
                "is_column_header": false,
                "is_projected_row_header": false,
                "pdf_bbox": [
                    403.9025573730469,
                    237.95034790039062,
                    417.9174499511719,
                    244.95034790039062
                ],
                "pdf_text_content": "4.4"
            },
            {
                "pdf_text_tight_bbox": [
                    438.6234436035156,
                    237.95034790039062,
                    447.3734436035156,
                    244.95034790039062
                ],
                "text_content": "4.3",
                "row_nums": [
                    3
                ],
                "column_nums": [
                    7
                ],
                "is_column_header": false,
                "is_projected_row_header": false,
                "pdf_bbox": [
                    433.3648681640625,
                    237.95034790039062,
                    447.3797607421875,
                    244.95034790039062
                ],
                "pdf_text_content": "4.3"
            },
            {
                "pdf_text_tight_bbox": [
                    468.0843505859375,
                    237.95034790039062,
                    476.8343505859375,
                    244.95034790039062
                ],
                "text_content": "4.1",
                "row_nums": [
                    3
                ],
                "column_nums": [
                    8
                ],
                "is_column_header": false,
                "is_projected_row_header": false,
                "pdf_bbox": [
                    462.8257751464844,
                    237.95034790039062,
                    476.8406677246094,
                    244.95034790039062
                ],
                "pdf_text_content": "4.1"
            },
            {
                "pdf_text_tight_bbox": [
                    497.5466613769531,
                    237.95034790039062,
                    506.2966613769531,
                    244.95034790039062
                ],
                "text_content": "4.0",
                "row_nums": [
                    3
                ],
                "column_nums": [
                    9
                ],
                "is_column_header": false,
                "is_projected_row_header": false,
                "pdf_bbox": [
                    492.2880859375,
                    237.95034790039062,
                    506.302978515625,
                    244.95034790039062
                ],
                "pdf_text_content": "4.0"
            },
            {
                "pdf_text_tight_bbox": [
                    527.0089721679688,
                    237.95034790039062,
                    535.7589721679688,
                    244.95034790039062
                ],
                "text_content": "3.9",
                "row_nums": [
                    3
                ],
                "column_nums": [
                    10
                ],
                "is_column_header": false,
                "is_projected_row_header": false,
                "pdf_bbox": [
                    521.7503662109375,
                    237.95034790039062,
                    535.7652587890625,
                    244.95034790039062
                ],
                "pdf_text_content": "3.9"
            },
            {
                "pdf_text_tight_bbox": [
                    150.2360076904297,
                    247.05526733398438,
                    238.49899291992188,
                    254.05526733398438
                ],
                "text_content": "Interest payments-to-GDP ratio",
                "row_nums": [
                    4
                ],
                "column_nums": [
                    0
                ],
                "is_column_header": false,
                "is_projected_row_header": false,
                "pdf_bbox": [
                    150.23599243164062,
                    247.05526733398438,
                    238.49899291992188,
                    254.05526733398438
                ],
                "pdf_text_content": "Interest payments-to-GDP ratio"
            },
            {
                "pdf_text_tight_bbox": [
                    261.848876953125,
                    247.05526733398438,
                    270.598876953125,
                    254.05526733398438
                ],
                "text_content": "4.1",
                "row_nums": [
                    4
                ],
                "column_nums": [
                    1
                ],
                "is_column_header": false,
                "is_projected_row_header": false,
                "pdf_bbox": [
                    256.59100341796875,
                    247.05526733398438,
                    270.60589599609375,
                    254.05526733398438
                ],
                "pdf_text_content": "4.1"
            },
            {
                "pdf_text_tight_bbox": [
                    291.3111877441406,
                    247.05526733398438,
                    300.0611877441406,
                    254.05526733398438
                ],
                "text_content": "5.0",
                "row_nums": [
                    4
                ],
                "column_nums": [
                    2
                ],
                "is_column_header": false,
                "is_projected_row_header": false,
                "pdf_bbox": [
                    286.0533142089844,
                    247.05526733398438,
                    300.0682067871094,
                    254.05526733398438
                ],
                "pdf_text_content": "5.0"
            },
            {
                "pdf_text_tight_bbox": [
                    320.77349853515625,
                    247.05526733398438,
                    329.52349853515625,
                    254.05526733398438
                ],
                "text_content": "5.2",
                "row_nums": [
                    4
                ],
                "column_nums": [
                    3
                ],
                "is_column_header": false,
                "is_projected_row_header": false,
                "pdf_bbox": [
                    315.515625,
                    247.05526733398438,
                    329.530517578125,
                    254.05526733398438
                ],
                "pdf_text_content": "5.2"
            },
            {
                "pdf_text_tight_bbox": [
                    350.2358093261719,
                    247.05526733398438,
                    358.9858093261719,
                    254.05526733398438
                ],
                "text_content": "5.1",
                "row_nums": [
                    4
                ],
                "column_nums": [
                    4
                ],
                "is_column_header": false,
                "is_projected_row_header": false,
                "pdf_bbox": [
                    344.9779357910156,
                    247.05526733398438,
                    358.9928283691406,
                    254.05526733398438
                ],
                "pdf_text_content": "5.1"
            },
            {
                "pdf_text_tight_bbox": [
                    379.6981201171875,
                    247.05526733398438,
                    388.4481201171875,
                    254.05526733398438
                ],
                "text_content": "5.0",
                "row_nums": [
                    4
                ],
                "column_nums": [
                    5
                ],
                "is_column_header": false,
                "is_projected_row_header": false,
                "pdf_bbox": [
                    374.44024658203125,
                    247.05526733398438,
                    388.45513916015625,
                    254.05526733398438
                ],
                "pdf_text_content": "5.0"
            },
            {
                "pdf_text_tight_bbox": [
                    409.1604309082031,
                    247.05526733398438,
                    417.9104309082031,
                    254.05526733398438
                ],
                "text_content": "4.9",
                "row_nums": [
                    4
                ],
                "column_nums": [
                    6
                ],
                "is_column_header": false,
                "is_projected_row_header": false,
                "pdf_bbox": [
                    403.9025573730469,
                    247.05526733398438,
                    417.9174499511719,
                    254.05526733398438
                ],
                "pdf_text_content": "4.9"
            },
            {
                "pdf_text_tight_bbox": [
                    438.62274169921875,
                    247.05526733398438,
                    447.37274169921875,
                    254.05526733398438
                ],
                "text_content": "4.7",
                "row_nums": [
                    4
                ],
                "column_nums": [
                    7
                ],
                "is_column_header": false,
                "is_projected_row_header": false,
                "pdf_bbox": [
                    433.3648681640625,
                    247.05526733398438,
                    447.3797607421875,
                    254.05526733398438
                ],
                "pdf_text_content": "4.7"
            },
            {
                "pdf_text_tight_bbox": [
                    468.0836486816406,
                    247.05526733398438,
                    476.8336486816406,
                    254.05526733398438
                ],
                "text_content": "4.6",
                "row_nums": [
                    4
                ],
                "column_nums": [
                    8
                ],
                "is_column_header": false,
                "is_projected_row_header": false,
                "pdf_bbox": [
                    462.8257751464844,
                    247.05526733398438,
                    476.8406677246094,
                    254.05526733398438
                ],
                "pdf_text_content": "4.6"
            },
            {
                "pdf_text_tight_bbox": [
                    497.54595947265625,
                    247.05526733398438,
                    506.29595947265625,
                    254.05526733398438
                ],
                "text_content": "4.5",
                "row_nums": [
                    4
                ],
                "column_nums": [
                    9
                ],
                "is_column_header": false,
                "is_projected_row_header": false,
                "pdf_bbox": [
                    492.2880859375,
                    247.05526733398438,
                    506.302978515625,
                    254.05526733398438
                ],
                "pdf_text_content": "4.5"
            },
            {
                "pdf_text_tight_bbox": [
                    527.0082397460938,
                    247.05526733398438,
                    535.7582397460938,
                    254.05526733398438
                ],
                "text_content": "4.4",
                "row_nums": [
                    4
                ],
                "column_nums": [
                    10
                ],
                "is_column_header": false,
                "is_projected_row_header": false,
                "pdf_bbox": [
                    521.7503662109375,
                    247.05526733398438,
                    535.7652587890625,
                    254.05526733398438
                ],
                "pdf_text_content": "4.4"
            },
            {
                "pdf_text_tight_bbox": [
                    150.2360076904297,
                    256.1608581542969,
                    237.50611877441406,
                    263.1608581542969
                ],
                "text_content": "Average effective interest rates",
                "row_nums": [
                    5
                ],
                "column_nums": [
                    0
                ],
                "is_column_header": false,
                "is_projected_row_header": false,
                "pdf_bbox": [
                    150.23599243164062,
                    256.1608581542969,
                    238.49899291992188,
                    263.1608581542969
                ],
                "pdf_text_content": "Average effective interest rates"
            },
            {
                "pdf_text_tight_bbox": [
                    261.85589599609375,
                    256.1608581542969,
                    270.60589599609375,
                    263.1608581542969
                ],
                "text_content": "4.4",
                "row_nums": [
                    5
                ],
                "column_nums": [
                    1
                ],
                "is_column_header": false,
                "is_projected_row_header": false,
                "pdf_bbox": [
                    256.59100341796875,
                    256.1608581542969,
                    270.60589599609375,
                    263.1608581542969
                ],
                "pdf_text_content": "4.4"
            },
            {
                "pdf_text_tight_bbox": [
                    291.3182067871094,
                    256.1608581542969,
                    300.0682067871094,
                    263.1608581542969
                ],
                "text_content": "4.6",
                "row_nums": [
                    5
                ],
                "column_nums": [
                    2
                ],
                "is_column_header": false,
                "is_projected_row_header": false,
                "pdf_bbox": [
                    286.0533142089844,
                    256.1608581542969,
                    300.0682067871094,
                    263.1608581542969
                ],
                "pdf_text_content": "4.6"
            },
            {
                "pdf_text_tight_bbox": [
                    320.780517578125,
                    256.1608581542969,
                    329.530517578125,
                    263.1608581542969
                ],
                "text_content": "4.7",
                "row_nums": [
                    5
                ],
                "column_nums": [
                    3
                ],
                "is_column_header": false,
                "is_projected_row_header": false,
                "pdf_bbox": [
                    315.515625,
                    256.1608581542969,
                    329.530517578125,
                    263.1608581542969
                ],
                "pdf_text_content": "4.7"
            },
            {
                "pdf_text_tight_bbox": [
                    350.2428283691406,
                    256.1608581542969,
                    358.9928283691406,
                    263.1608581542969
                ],
                "text_content": "4.6",
                "row_nums": [
                    5
                ],
                "column_nums": [
                    4
                ],
                "is_column_header": false,
                "is_projected_row_header": false,
                "pdf_bbox": [
                    344.9779357910156,
                    256.1608581542969,
                    358.9928283691406,
                    263.1608581542969
                ],
                "pdf_text_content": "4.6"
            },
            {
                "pdf_text_tight_bbox": [
                    379.70513916015625,
                    256.1608581542969,
                    388.45513916015625,
                    263.1608581542969
                ],
                "text_content": "4.6",
                "row_nums": [
                    5
                ],
                "column_nums": [
                    5
                ],
                "is_column_header": false,
                "is_projected_row_header": false,
                "pdf_bbox": [
                    374.44024658203125,
                    256.1608581542969,
                    388.45513916015625,
                    263.1608581542969
                ],
                "pdf_text_content": "4.6"
            },
            {
                "pdf_text_tight_bbox": [
                    409.1674499511719,
                    256.1608581542969,
                    417.9174499511719,
                    263.1608581542969
                ],
                "text_content": "4.6",
                "row_nums": [
                    5
                ],
                "column_nums": [
                    6
                ],
                "is_column_header": false,
                "is_projected_row_header": false,
                "pdf_bbox": [
                    403.9025573730469,
                    256.1608581542969,
                    417.9174499511719,
                    263.1608581542969
                ],
                "pdf_text_content": "4.6"
            },
            {
                "pdf_text_tight_bbox": [
                    438.6297607421875,
                    256.1608581542969,
                    447.3797607421875,
                    263.1608581542969
                ],
                "text_content": "4.6",
                "row_nums": [
                    5
                ],
                "column_nums": [
                    7
                ],
                "is_column_header": false,
                "is_projected_row_header": false,
                "pdf_bbox": [
                    433.3648681640625,
                    256.1608581542969,
                    447.3797607421875,
                    263.1608581542969
                ],
                "pdf_text_content": "4.6"
            },
            {
                "pdf_text_tight_bbox": [
                    468.0906677246094,
                    256.1608581542969,
                    476.8406677246094,
                    263.1608581542969
                ],
                "text_content": "4.6",
                "row_nums": [
                    5
                ],
                "column_nums": [
                    8
                ],
                "is_column_header": false,
                "is_projected_row_header": false,
                "pdf_bbox": [
                    462.8257751464844,
                    256.1608581542969,
                    476.8406677246094,
                    263.1608581542969
                ],
                "pdf_text_content": "4.6"
            },
            {
                "pdf_text_tight_bbox": [
                    497.552978515625,
                    256.1608581542969,
                    506.302978515625,
                    263.1608581542969
                ],
                "text_content": "4.6",
                "row_nums": [
                    5
                ],
                "column_nums": [
                    9
                ],
                "is_column_header": false,
                "is_projected_row_header": false,
                "pdf_bbox": [
                    492.2880859375,
                    256.1608581542969,
                    506.302978515625,
                    263.1608581542969
                ],
                "pdf_text_content": "4.6"
            },
            {
                "pdf_text_tight_bbox": [
                    527.0152587890625,
                    256.1608581542969,
                    535.7652587890625,
                    263.1608581542969
                ],
                "text_content": "4.6",
                "row_nums": [
                    5
                ],
                "column_nums": [
                    10
                ],
                "is_column_header": false,
                "is_projected_row_header": false,
                "pdf_bbox": [
                    521.7503662109375,
                    256.1608581542969,
                    535.7652587890625,
                    263.1608581542969
                ],
                "pdf_text_content": "4.6"
            },
            {
                "pdf_text_tight_bbox": [
                    150.2360076904297,
                    265.2657775878906,
                    228.7760009765625,
                    272.2657775878906
                ],
                "text_content": "Fiscal balance-to-GDP ratio",
                "row_nums": [
                    6
                ],
                "column_nums": [
                    0
                ],
                "is_column_header": false,
                "is_projected_row_header": false,
                "pdf_bbox": [
                    150.23599243164062,
                    265.2657775878906,
                    238.49899291992188,
                    272.2657775878906
                ],
                "pdf_text_content": "Fiscal balance-to-GDP ratio"
            },
            {
                "pdf_text_tight_bbox": [
                    259.51861572265625,
                    265.2657775878906,
                    270.599609375,
                    272.2657775878906
                ],
                "text_content": "-4.0",
                "row_nums": [
                    6
                ],
                "column_nums": [
                    1
                ],
                "is_column_header": false,
                "is_projected_row_header": false,
                "pdf_bbox": [
                    256.59100341796875,
                    265.2657775878906,
                    270.60589599609375,
                    272.2657775878906
                ],
                "pdf_text_content": "-4.0"
            },
            {
                "pdf_text_tight_bbox": [
                    288.980224609375,
                    265.2657775878906,
                    300.06121826171875,
                    272.2657775878906
                ],
                "text_content": "-4.5",
                "row_nums": [
                    6
                ],
                "column_nums": [
                    2
                ],
                "is_column_header": false,
                "is_projected_row_header": false,
                "pdf_bbox": [
                    286.0533142089844,
                    265.2657775878906,
                    300.0682067871094,
                    272.2657775878906
                ],
                "pdf_text_content": "-4.5"
            },
            {
                "pdf_text_tight_bbox": [
                    318.4425048828125,
                    265.2657775878906,
                    329.52349853515625,
                    272.2657775878906
                ],
                "text_content": "-3.0",
                "row_nums": [
                    6
                ],
                "column_nums": [
                    3
                ],
                "is_column_header": false,
                "is_projected_row_header": false,
                "pdf_bbox": [
                    315.515625,
                    265.2657775878906,
                    329.530517578125,
                    272.2657775878906
                ],
                "pdf_text_content": "-3.0"
            },
            {
                "pdf_text_tight_bbox": [
                    347.90478515625,
                    265.2657775878906,
                    358.98577880859375,
                    272.2657775878906
                ],
                "text_content": "-1.8",
                "row_nums": [
                    6
                ],
                "column_nums": [
                    4
                ],
                "is_column_header": false,
                "is_projected_row_header": false,
                "pdf_bbox": [
                    344.9779357910156,
                    265.2657775878906,
                    358.9928283691406,
                    272.2657775878906
                ],
                "pdf_text_content": "-1.8"
            },
            {
                "pdf_text_tight_bbox": [
                    377.3670654296875,
                    265.2657775878906,
                    388.44805908203125,
                    272.2657775878906
                ],
                "text_content": "-0.5",
                "row_nums": [
                    6
                ],
                "column_nums": [
                    5
                ],
                "is_column_header": false,
                "is_projected_row_header": false,
                "pdf_bbox": [
                    374.44024658203125,
                    265.2657775878906,
                    388.45513916015625,
                    272.2657775878906
                ],
                "pdf_text_content": "-0.5"
            },
            {
                "pdf_text_tight_bbox": [
                    406.829345703125,
                    265.2657775878906,
                    417.91033935546875,
                    272.2657775878906
                ],
                "text_content": "-0.5",
                "row_nums": [
                    6
                ],
                "column_nums": [
                    6
                ],
                "is_column_header": false,
                "is_projected_row_header": false,
                "pdf_bbox": [
                    403.9025573730469,
                    265.2657775878906,
                    417.9174499511719,
                    272.2657775878906
                ],
                "pdf_text_content": "-0.5"
            },
            {
                "pdf_text_tight_bbox": [
                    436.2902526855469,
                    265.2657775878906,
                    447.3712463378906,
                    272.2657775878906
                ],
                "text_content": "-0.5",
                "row_nums": [
                    6
                ],
                "column_nums": [
                    7
                ],
                "is_column_header": false,
                "is_projected_row_header": false,
                "pdf_bbox": [
                    433.3648681640625,
                    265.2657775878906,
                    447.3797607421875,
                    272.2657775878906
                ],
                "pdf_text_content": "-0.5"
            },
            {
                "pdf_text_tight_bbox": [
                    465.7525329589844,
                    265.2657775878906,
                    476.8335266113281,
                    272.2657775878906
                ],
                "text_content": "-0.5",
                "row_nums": [
                    6
                ],
                "column_nums": [
                    8
                ],
                "is_column_header": false,
                "is_projected_row_header": false,
                "pdf_bbox": [
                    462.8257751464844,
                    265.2657775878906,
                    476.8406677246094,
                    272.2657775878906
                ],
                "pdf_text_content": "-0.5"
            },
            {
                "pdf_text_tight_bbox": [
                    495.214111328125,
                    265.2657775878906,
                    506.29510498046875,
                    272.2657775878906
                ],
                "text_content": "-0.5",
                "row_nums": [
                    6
                ],
                "column_nums": [
                    9
                ],
                "is_column_header": false,
                "is_projected_row_header": false,
                "pdf_bbox": [
                    492.2880859375,
                    265.2657775878906,
                    506.302978515625,
                    272.2657775878906
                ],
                "pdf_text_content": "-0.5"
            },
            {
                "pdf_text_tight_bbox": [
                    524.6763916015625,
                    265.2657775878906,
                    535.7573852539062,
                    272.2657775878906
                ],
                "text_content": "-0.5",
                "row_nums": [
                    6
                ],
                "column_nums": [
                    10
                ],
                "is_column_header": false,
                "is_projected_row_header": false,
                "pdf_bbox": [
                    521.7503662109375,
                    265.2657775878906,
                    535.7652587890625,
                    272.2657775878906
                ],
                "pdf_text_content": "-0.5"
            },
            {
                "pdf_text_tight_bbox": [],
                "text_content": "",
                "row_nums": [
                    0
                ],
                "column_nums": [
                    0
                ],
                "is_column_header": true,
                "is_projected_row_header": false,
                "pdf_bbox": [
                    150.23599243164062,
                    206.41184997558594,
                    238.49899291992188,
                    213.41184997558594
                ],
                "pdf_text_content": ""
            }
        ],
        "rows": {
            "0": {
                "is_column_header": true,
                "is_projected_row_header": false,
                "pdf_row_bbox": [
                    150.23599243164062,
                    206.41184997558594,
                    535.7652587890625,
                    213.41184997558594
                ]
            },
            "1": {
                "is_column_header": false,
                "is_projected_row_header": false,
                "pdf_row_bbox": [
                    150.23599243164062,
                    219.73983764648438,
                    535.7652587890625,
                    226.73983764648438
                ]
            },
            "2": {
                "is_column_header": false,
                "is_projected_row_header": false,
                "pdf_row_bbox": [
                    150.23599243164062,
                    228.84475708007812,
                    535.7652587890625,
                    235.84475708007812
                ]
            },
            "3": {
                "is_column_header": false,
                "is_projected_row_header": false,
                "pdf_row_bbox": [
                    150.23599243164062,
                    237.95034790039062,
                    535.7652587890625,
                    244.95034790039062
                ]
            },
            "4": {
                "is_column_header": false,
                "is_projected_row_header": false,
                "pdf_row_bbox": [
                    150.23599243164062,
                    247.05526733398438,
                    535.7652587890625,
                    254.05526733398438
                ]
            },
            "5": {
                "is_column_header": false,
                "is_projected_row_header": false,
                "pdf_row_bbox": [
                    150.23599243164062,
                    256.1608581542969,
                    535.7652587890625,
                    263.1608581542969
                ]
            },
            "6": {
                "is_column_header": false,
                "is_projected_row_header": false,
                "pdf_row_bbox": [
                    150.23599243164062,
                    265.2657775878906,
                    535.7652587890625,
                    272.2657775878906
                ]
            }
        },
        "columns": {
            "0": {
                "pdf_column_bbox": [
                    150.23599243164062,
                    206.41184997558594,
                    238.49899291992188,
                    272.2657775878906
                ]
            },
            "1": {
                "pdf_column_bbox": [
                    256.59100341796875,
                    206.41184997558594,
                    270.60589599609375,
                    272.2657775878906
                ]
            },
            "2": {
                "pdf_column_bbox": [
                    286.0533142089844,
                    206.41184997558594,
                    300.0682067871094,
                    272.2657775878906
                ]
            },
            "3": {
                "pdf_column_bbox": [
                    315.515625,
                    206.41184997558594,
                    329.530517578125,
                    272.2657775878906
                ]
            },
            "4": {
                "pdf_column_bbox": [
                    344.9779357910156,
                    206.41184997558594,
                    358.9928283691406,
                    272.2657775878906
                ]
            },
            "5": {
                "pdf_column_bbox": [
                    374.44024658203125,
                    206.41184997558594,
                    388.45513916015625,
                    272.2657775878906
                ]
            },
            "6": {
                "pdf_column_bbox": [
                    403.9025573730469,
                    206.41184997558594,
                    417.9174499511719,
                    272.2657775878906
                ]
            },
            "7": {
                "pdf_column_bbox": [
                    433.3648681640625,
                    206.41184997558594,
                    447.3797607421875,
                    272.2657775878906
                ]
            },
            "8": {
                "pdf_column_bbox": [
                    462.8257751464844,
                    206.41184997558594,
                    476.8406677246094,
                    272.2657775878906
                ]
            },
            "9": {
                "pdf_column_bbox": [
                    492.2880859375,
                    206.41184997558594,
                    506.302978515625,
                    272.2657775878906
                ]
            },
            "10": {
                "pdf_column_bbox": [
                    521.7503662109375,
                    206.41184997558594,
                    535.7652587890625,
                    272.2657775878906
                ]
            }
        },
        "pdf_page_index": 1,
        "icdar2013_source_table_id": "0",
        "icdar2013_source_region_id": "0",
        "exclude_for_structure": false,
        "exclude_for_detection": false,
        "split": "val",
        "pdf_file_name": "eu-dataset\\eu-027.pdf",
        "pdf_folder": "ICDAR-2013-Table-Competition-Corrected/",
        "document_id": "ICDAR-2013-Table-Competition-Corrected_eu-dataset\\eu-027",
        "icdar2013_source_file_name": "eu-dataset\\eu-027-str.xml",
        "pdf_full_page_bbox": [
            0.0,
            0.0,
            595.2760009765625,
            841.8900146484375
        ],
        "document_table_index": 0,
        "structure_id": "ICDAR-2013-Table-Competition-Corrected_eu-dataset\\eu-027_0",
        "pdf_table_bbox": [
            150.23599243164062,
            206.41184997558594,
            535.7652587890625,
            272.2657775878906
        ]
    }
]